confopt/__init__.py
confopt/tuning.py
confopt/wrapping.py
confopt/selection/__init__.py
confopt/selection/acquisition.py
confopt/selection/adaptation.py
confopt/selection/conformalization.py
confopt/selection/estimation.py
confopt/selection/estimator_configuration.py
confopt/selection/estimators/__init__.py
confopt/selection/estimators/ensembling.py
confopt/selection/estimators/quantile_estimation.py
confopt/selection/sampling/__init__.py
confopt/selection/sampling/bound_samplers.py
confopt/selection/sampling/expected_improvement_samplers.py
confopt/selection/sampling/thompson_samplers.py
confopt/selection/sampling/utils.py
confopt/utils/__init__.py
confopt/utils/optimization.py
confopt/utils/preprocessing.py
confopt/utils/tracking.py
confopt/utils/configurations/__init__.py
confopt/utils/configurations/encoding.py
confopt/utils/configurations/sampling.py
confopt/utils/configurations/utils.py
confopt-2.0.1.dist-info/licenses/LICENSE
confopt-2.0.1.dist-info/METADATA
confopt-2.0.1.dist-info/WHEEL
confopt-2.0.1.dist-info/top_level.txt
confopt-2.0.1.dist-info/RECORD
