Metadata-Version: 2.4
Name: confopt
Version: 2.0.1
Summary: Conformal hyperparameter optimization tool
Author-email: Riccardo Doyle <r.doyle.edu@gmail.com>
Project-URL: Source, https://github.com/rick12000/confopt
Project-URL: Documentation, https://confopt.readthedocs.io
Project-URL: Changelog, https://github.com/rick12000/confopt/releases
Classifier: Programming Language :: Python :: 3.9
Classifier: Programming Language :: Python :: 3.10
Classifier: Programming Language :: Python :: 3.11
Classifier: Programming Language :: Python :: 3.12
Requires-Python: >=3.9
License-File: LICENSE
Requires-Dist: numpy>=1.20.0
Requires-Dist: scikit-learn>=1.0.0
Requires-Dist: scipy>=1.7.0
Requires-Dist: pandas>=1.3.0
Requires-Dist: tqdm>=4.60.0
Requires-Dist: pydantic>=2.0.0
Requires-Dist: statsmodels>=0.13.0
Provides-Extra: dev
Requires-Dist: pytest>=7.4.0; extra == "dev"
Requires-Dist: pytest-xdist>=3.0.0; extra == "dev"
Requires-Dist: pre-commit>=3.4.0; extra == "dev"
Requires-Dist: autoflake>=2.0.0; extra == "dev"
Provides-Extra: docs
Requires-Dist: sphinx>=5.0.0; extra == "docs"
Requires-Dist: sphinx-rtd-theme>=1.3.0; extra == "docs"
Requires-Dist: myst-parser>=2.0.0; extra == "docs"
Requires-Dist: sphinx-copybutton>=0.5.0; extra == "docs"
Requires-Dist: sphinxcontrib-mermaid>=0.8.0; extra == "docs"
Requires-Dist: sphinx-autobuild>=2024.10.3; extra == "docs"
Dynamic: license-file
